zoomaker.py
zoomaker-0.10.2.dist-info/METADATA
zoomaker-0.10.2.dist-info/WHEEL
zoomaker-0.10.2.dist-info/entry_points.txt
zoomaker-0.10.2.dist-info/RECORD
