Metadata-Version: 2.1
Name: zoomaker
Version: 0.10.2
Summary: Zoomaker - Friendly house keeping for your AI model zoo and related resources.
Home-page: https://github.com/hfg-gmuend/zoomaker
Author: Benedikt Groß
Requires-Python: >=3.9,<4.0
Classifier: Programming Language :: Python :: 3
Classifier: Programming Language :: Python :: 3.9
Classifier: Programming Language :: Python :: 3.10
Classifier: Programming Language :: Python :: 3.11
Requires-Dist: GitPython (>=3.1.43,<4.0.0)
Requires-Dist: huggingface-hub (>=0.23.0,<0.24.0)
Project-URL: Documentation, https://github.com/hfg-gmuend/zoomaker
Project-URL: Repository, https://github.com/hfg-gmuend/zoomaker
